.gitignore
.travis.yml
CHANGES.txt
LICENSE.txt
README.rst
setup.cfg
setup.py
tox.ini
examples/like_5_users.py
examples/like_recent_messages.py
examples/tinder_social_examples.py
examples/dump_conversation/dump.py
examples/dump_conversation/requirements.txt
pynder/__init__.py
pynder/api.py
pynder/constants.py
pynder/errors.py
pynder/session.py
pynder.egg-info/PKG-INFO
pynder.egg-info/SOURCES.txt
pynder.egg-info/dependency_links.txt
pynder.egg-info/requires.txt
pynder.egg-info/top_level.txt
pynder/models/__init__.py
pynder/models/friend.py
pynder/models/me.py
pynder/models/message.py
pynder/models/user.py
pynder/tests/__init__.py
pynder/tests/test.ini.sample
pynder/tests/test_session.py
pynder/tests/utils.py
pynder/tests/vcr/session/test_login
pynder/tests/vcr/session/test_nearby_users_empty