Metadata-Version: 1.1
Name: pynder
Version: 0.0.13
Summary: A client for the tinder api
Home-page: https://github.com/charliewolf/pynder
Author: Charlie Wolf
Author-email: charlie@wolf.is
License: Tequila-ware Rev.44
Keywords: tinder,online dating
Platform: UNKNOWN
Classifier: Development Status :: 3 - Alpha
Classifier: License :: OSI Approved :: MIT License
Classifier: Programming Language :: Python :: 2
Classifier: Programming Language :: Python :: 3
Classifier: Topic :: Utilities
